django_bulk_drf/__init__.py
django_bulk_drf/exceptions.py
django_bulk_drf/mixins.py
django_bulk_drf/monitoring.py
django_bulk_drf/operations.py
django_bulk_drf/queries.py
django_bulk_drf/relations.py
django_bulk_drf/results.py
django_bulk_drf/routers.py
django_bulk_drf/serializers.py
django_bulk_drf/settings.py
django_bulk_drf/transactions.py
django_bulk_drf/utils.py
django_bulk_drf/validators.py
django_bulk_drf/viewsets.py
django_bulk_drf-0.2.80.dist-info/LICENSE
django_bulk_drf-0.2.80.dist-info/METADATA
django_bulk_drf-0.2.80.dist-info/WHEEL
django_bulk_drf-0.2.80.dist-info/RECORD
